DeltacodeProject/Deltacode.py
DeltacodeProject/DeltacodeNew.py
DeltacodeProject/__init__.py
DeltacodeProject/__main__.py
DeltacodeProject/encodings/__init__.py
DeltacodeProject/encodings/_encodings.py
DeltacodeProject/encodings/_encodings2.py
DeltacodeProject/encodings/_encodings3.py
DeltacodeProject/encodings/_new_encoding.py
DeltacodeProject/game/__init__.py
DeltacodeProject/game/__main__.py
DeltacodeProject/game/game.py
DeltacodeProject/game/play.py
DeltacodeProject/gui/GUI.py
DeltacodeProject/gui/__init__.py
DeltacodeProject/gui/open_file.py
DeltacodeProject/scripts/__init__.py
DeltacodeProject/scripts/copy.py
DeltacodeProject/scripts/exts.py
DeltacodeProject/scripts/find.py
DeltacodeProject/scripts/loading.py
DeltacodeProject/scripts/no_accent_char.py
DeltacodeProject/scripts/print_color.py
DeltacodeProject/scripts/signal_handler.py
DeltacodeProject/utilities/__init__.py
DeltacodeProject/utilities/decode.py
DeltacodeProject/utilities/encode.py
DeltacodeProject-0.7.32.3.dist-info/LICENSE
DeltacodeProject-0.7.32.3.dist-info/METADATA
DeltacodeProject-0.7.32.3.dist-info/WHEEL
DeltacodeProject-0.7.32.3.dist-info/top_level.txt
DeltacodeProject-0.7.32.3.dist-info/RECORD
