Metadata-Version: 2.1
Name: DeltacodeProject
Version: 0.7.32.3
Summary: Encoder et décoder du texte à l'aide de plusieurs types d'encodages
Home-page: https://github.com/daisseur/Deltacode_project
Author: daisseur
Author-email: daisseur@gmail.com
License: MIT License
Keywords: python,deltacode,code,coding,encoding,DayEncoding,ROT,Cesar,DeltacodeProject,project,delta
Classifier: Intended Audience :: Developers
Classifier: Programming Language :: Python :: 3
Classifier: Operating System :: Unix
Classifier: Operating System :: Microsoft :: Windows
License-File: LICENSE
